Metadata-Version: 2.1
Name: ashishbansal-101703113-outlier-removal
Version: 0.0.1
Summary: A small package that removes outliers from a pandas dataframe
Home-page: UNKNOWN
Author: Ashish Bansal
Author-email: abansal2_be17@thapar.edu
License: UNKNOWN
Platform: UNKNOWN
Classifier: Programming Language :: Python :: 3
Classifier: License :: OSI Approved :: MIT License
Classifier: Operating System :: OS Independent
Requires-Python: >=3.6
